example/__init__.py
example/inner_window.py
example/slide.py
example/themeCreator.py
example/top_window.py
xtkinter/__init__.py
xtkinter/__pycache__/__init__.cpython-311.pyc
xtkinter/assets/window.png
xtkinter/assets/icon/favicon.ico
xtkinter/assets/image/Sizegrip.gif
xtkinter/utility/__init__.py
xtkinter/utility/style.py
xtkinter/utility/utility_func.py
xtkinter/utility/__pycache__/__init__.cpython-311.pyc
xtkinter/utility/__pycache__/style.cpython-311.pyc
xtkinter/utility/__pycache__/utility_func.cpython-311.pyc
xtkinter/widgets/__init__.py
xtkinter/widgets/xtk_frame.py
xtkinter/widgets/xtk_sizegrip.py
xtkinter/widgets/__pycache__/__init__.cpython-311.pyc
xtkinter/widgets/__pycache__/xtk_frame.cpython-311.pyc
xtkinter/widgets/__pycache__/xtk_sizegrip.cpython-311.pyc
xtkinter/windows/__init__.py
xtkinter/windows/xtk_inner_window.py
xtkinter/windows/xtk_tk.py
xtkinter/windows/xtk_toplevel.py
xtkinter/windows/__pycache__/__init__.cpython-311.pyc
xtkinter/windows/__pycache__/xtk_inner_window.cpython-311.pyc
xtkinter/windows/__pycache__/xtk_tk.cpython-311.pyc
xtkinter/windows/__pycache__/xtk_toplevel.cpython-311.pyc
xtkinter/xtkthemes/__init__.py
xtkinter/xtkthemes/themeCreator.py
xtkinter/xtkthemes/themed_base_class.py
xtkinter/xtkthemes/utils.py
xtkinter/xtkthemes/xtk_themes.py
xtkinter/xtkthemes/__pycache__/__init__.cpython-311.pyc
xtkinter/xtkthemes/__pycache__/themeCreator.cpython-311.pyc
xtkinter/xtkthemes/__pycache__/themed_base_class.cpython-311.pyc
xtkinter/xtkthemes/__pycache__/utils.cpython-311.pyc
xtkinter/xtkthemes/__pycache__/xtk_themes.cpython-311.pyc
xtkinter/xtkthemes/template/themeTemplate.tcl
xtkinter/xtkthemes/template/themeTemplate/Menubutton-disabled.png
xtkinter/xtkthemes/template/themeTemplate/Menubutton-hover.png
xtkinter/xtkthemes/template/themeTemplate/Menubutton-normal.png
xtkinter/xtkthemes/template/themeTemplate/Menubutton-pressed.png
xtkinter/xtkthemes/template/themeTemplate/arrow-down-active.png
xtkinter-1.0.6.dist-info/LICENSE
xtkinter-1.0.6.dist-info/METADATA
xtkinter-1.0.6.dist-info/WHEEL
xtkinter-1.0.6.dist-info/top_level.txt
xtkinter-1.0.6.dist-info/RECORD
