Metadata-Version: 2.1
Name: xtkinter
Version: 1.0.6
Summary: 一个基于tkinter包的扩展模块，可以更加自由的定义各种窗口及美化小部件，使用xtkinter包可以做出更漂亮的图形界面
Home-page: https://gitee.com/yuhypython/xtkinter
Author: yuhaiyang
Author-email: 421142953@qq.com
Classifier: Programming Language :: Python :: 3
Classifier: License :: OSI Approved :: MIT License
Classifier: Operating System :: OS Independent
License-File: LICENSE
